{
  "$schema": "../node_modules/@tauri-apps/cli/schema/acl/capabilities.json",
  "identifier": "default",
  "description": "bams-widget 기본 퍼미션",
  "windows": ["popover"],
  "permissions": [
    "core:default",
    "core:window:allow-show",
    "core:window:allow-hide",
    "core:window:allow-set-size",
    "core:window:allow-set-position",
    "core:window:allow-close",
    "core:tray:default",
    "notification:default",
    "autostart:allow-enable",
    "autostart:allow-disable",
    "autostart:allow-is-enabled",
    "global-shortcut:allow-register",
    "global-shortcut:allow-unregister",
    "global-shortcut:allow-is-registered",
    "opener:allow-open-url"
  ]
}
